dt/__init__.py
dt/__main__.py
springbuk_de_bucket_download_5-0.0.1.dist-info/LICENSE
springbuk_de_bucket_download_5-0.0.1.dist-info/METADATA
springbuk_de_bucket_download_5-0.0.1.dist-info/WHEEL
springbuk_de_bucket_download_5-0.0.1.dist-info/top_level.txt
springbuk_de_bucket_download_5-0.0.1.dist-info/RECORD
