Metadata-Version: 2.1
Name: springbuk-de-bucket-download-5
Version: 0.0.1
Summary: tool to download s3 buckets
Home-page: https://github.com/EnriqueGalindo/springbuk_de_bucket_download
Author: Enrique Galindo
Author-email: egalindo@springbuk.com
License: UNKNOWN
Platform: UNKNOWN
